ChangeLog
LICENSE
MANIFEST.in
README.rst
setup.py
docs/Makefile
docs/requirements.txt
docs/source/changelog.rst
docs/source/conf.py
docs/source/datatypes.rst
docs/source/dom.rst
docs/source/duration.rst
docs/source/features.rst
docs/source/index.rst
docs/source/key.rst
docs/source/lang.rst
docs/source/license.rst
docs/source/modoverview.rst
docs/source/node.rst
docs/source/numbering.rst
docs/source/overview.rst
docs/source/pitch.rst
docs/source/pkginfo.rst
docs/source/quick-ly.png
docs/source/quick-ly.svg
docs/source/quickly-screenshot.jpg
docs/source/quickly.rst
docs/source/quicklydom.rst
docs/source/relative.rst
docs/source/rhythm.rst
docs/source/time.rst
docs/source/transpose.rst
docs/source/dom/base.rst
docs/source/dom/edit.rst
docs/source/dom/element.rst
docs/source/dom/htm.rst
docs/source/dom/indent.rst
docs/source/dom/lily.rst
docs/source/dom/markup.rst
docs/source/dom/read.rst
docs/source/dom/scm.rst
docs/source/dom/scope.rst
docs/source/dom/tex.rst
docs/source/dom/util.rst
docs/source/lang/html.rst
docs/source/lang/latex.rst
docs/source/lang/lilypond.rst
docs/source/lang/scheme.rst
quickly/__init__.py
quickly/datatypes.py
quickly/duration.py
quickly/key.py
quickly/node.py
quickly/numbering.py
quickly/pitch.py
quickly/pkginfo.py
quickly/relative.py
quickly/rhythm.py
quickly/time.py
quickly/transpose.py
quickly.egg-info/PKG-INFO
quickly.egg-info/SOURCES.txt
quickly.egg-info/dependency_links.txt
quickly.egg-info/top_level.txt
quickly/dom/__init__.py
quickly/dom/base.py
quickly/dom/edit.py
quickly/dom/element.py
quickly/dom/htm.py
quickly/dom/indent.py
quickly/dom/lily.py
quickly/dom/markup.py
quickly/dom/read.py
quickly/dom/scm.py
quickly/dom/scope.py
quickly/dom/tex.py
quickly/dom/util.py
quickly/lang/__init__.py
quickly/lang/html.py
quickly/lang/latex.py
quickly/lang/lilypond.py
quickly/lang/scheme.py
tests/test_dom.py
tests/test_dom_edit.py
tests/test_dom_util.py
tests/test_duration.py
tests/test_indent.py
tests/test_key.py
tests/test_node.py
tests/test_numbering.py
tests/test_pitch.py
tests/test_rhythm.py
tests/test_scheme.py
tests/test_template.py
tests/test_time.py