Metadata-Version: 1.2
Name: quickly
Version: 0.7.0
Summary: Tool and library for manipulating LilyPond files
Home-page: https://quick-ly.info/
Maintainer: Wilbert Berendsen
Maintainer-email: info@frescobaldi.org
License: GPL v3
Platform: UNKNOWN
Classifier: Development Status :: 3 - Alpha
Classifier: Intended Audience :: Developers
Classifier: License :: OSI Approved :: GNU General Public License v3 or later (GPLv3+)
Classifier: Operating System :: MacOS :: MacOS X
Classifier: Operating System :: Microsoft :: Windows
Classifier: Operating System :: POSIX
Classifier: Programming Language :: Python :: 3.6
Classifier: Topic :: Multimedia :: Sound/Audio
Classifier: Topic :: Text Processing
Classifier: Topic :: Text Editors
